docs/README.md
docs/USER_GUIDE.md
examples/cross_validation.py
examples/quickstart.py
examples/notebooks/tutorial.ipynb
scripts/build.sh
scripts/deploy.sh
scripts/quick_deploy.sh
tests/__init__.py
tests/test_dataset.py
tests/test_model.py
tests/test_unidq.py
unidq/__init__.py
unidq/config.py
unidq/dataset.py
unidq/evaluation.py
unidq/model.py
unidq/trainer.py
unidq-0.2.0.dist-info/LICENSE
unidq-0.2.0.dist-info/METADATA
unidq-0.2.0.dist-info/WHEEL
unidq-0.2.0.dist-info/top_level.txt
unidq-0.2.0.dist-info/RECORD
