Metadata-Version: 2.1
Name: unidq
Version: 0.2.0
Summary: Unified transformer for multi-task tabular data quality
Author-email: Shiva Koreddi <shivacse14@gmail.com>, Sravani Sowrupilli <sravani.sowrupilli@gmail.com>
License: MIT
Project-URL: Homepage, https://github.com/Shivakoreddi/unidq
Project-URL: Documentation, https://github.com/Shivakoreddi/unidq#readme
Project-URL: Repository, https://github.com/Shivakoreddi/unidq
Project-URL: Bug Tracker, https://github.com/Shivakoreddi/unidq/issues
Keywords: data-quality,error-detection,data-repair,imputation,label-noise,transformer,multi-task-learning,tabular-data
Classifier: Development Status :: 4 - Beta
Classifier: Intended Audience :: Developers
Classifier: Intended Audience :: Science/Research
Classifier: License :: OSI Approved :: MIT License
Classifier: Operating System :: OS Independent
Classifier: Programming Language :: Python :: 3
Classifier: Programming Language :: Python :: 3.8
Classifier: Programming Language :: Python :: 3.9
Classifier: Programming Language :: Python :: 3.10
Classifier: Programming Language :: Python :: 3.11
Classifier: Topic :: Scientific/Engineering :: Artificial Intelligence
Requires-Python: >=3.8
License-File: LICENSE
Requires-Dist: torch>=1.9.0
Requires-Dist: numpy>=1.19.0
Requires-Dist: pandas>=1.0.0
Requires-Dist: scikit-learn>=0.24.0
Requires-Dist: tqdm>=4.50.0
Provides-Extra: dev
Requires-Dist: pytest>=6.0; extra == "dev"
Requires-Dist: pytest-cov>=2.0; extra == "dev"
Requires-Dist: black>=21.0; extra == "dev"
Requires-Dist: flake8>=3.9; extra == "dev"
Requires-Dist: mypy>=0.900; extra == "dev"
Requires-Dist: build>=0.7.0; extra == "dev"
Requires-Dist: twine>=3.4.0; extra == "dev"
Provides-Extra: docs
Requires-Dist: sphinx>=4.0; extra == "docs"
Requires-Dist: sphinx-rtd-theme>=1.0; extra == "docs"
Provides-Extra: examples
Requires-Dist: matplotlib>=3.0; extra == "examples"
Requires-Dist: seaborn>=0.11; extra == "examples"
Requires-Dist: jupyter>=1.0; extra == "examples"
